TikTokApi/__init__.py
TikTokApi/exceptions.py
TikTokApi/helpers.py
TikTokApi/tiktok.py
TikTokApi/api/__init__.py
TikTokApi/api/comment.py
TikTokApi/api/hashtag.py
TikTokApi/api/search.py
TikTokApi/api/sound.py
TikTokApi/api/trending.py
TikTokApi/api/user.py
TikTokApi/api/video.py
TikTokApi/stealth/__init__.py
TikTokApi/stealth/stealth.py
TikTokApi/stealth/js/__init__.py
TikTokApi/stealth/js/chrome_app.py
TikTokApi/stealth/js/chrome_csi.py
TikTokApi/stealth/js/chrome_hairline.py
TikTokApi/stealth/js/chrome_load_times.py
TikTokApi/stealth/js/chrome_runtime.py
TikTokApi/stealth/js/generate_magic_arrays.py
TikTokApi/stealth/js/iframe_contentWindow.py
TikTokApi/stealth/js/media_codecs.py
TikTokApi/stealth/js/navigator_hardwareConcurrency.py
TikTokApi/stealth/js/navigator_languages.py
TikTokApi/stealth/js/navigator_permissions.py
TikTokApi/stealth/js/navigator_platform.py
TikTokApi/stealth/js/navigator_plugins.py
TikTokApi/stealth/js/navigator_userAgent.py
TikTokApi/stealth/js/navigator_vendor.py
TikTokApi/stealth/js/utils.py
TikTokApi/stealth/js/webgl_vendor.py
TikTokApi/stealth/js/window_outerdimensions.py
tests/__init__.py
tests/test_comments.py
tests/test_hashtag.py
tests/test_integration.py
tests/test_search.py
tests/test_sound.py
tests/test_trending.py
tests/test_user.py
tests/test_video.py
TikTokApi-6.5.1.dist-info/LICENSE
TikTokApi-6.5.1.dist-info/LICENSE.txt
TikTokApi-6.5.1.dist-info/METADATA
TikTokApi-6.5.1.dist-info/WHEEL
TikTokApi-6.5.1.dist-info/top_level.txt
TikTokApi-6.5.1.dist-info/RECORD
