Metadata-Version: 2.1
Name: TikTokApi
Version: 6.5.1
Summary: The Unofficial TikTok API Wrapper in Python 3.
Home-page: https://github.com/davidteather/tiktok-api
Download-URL: https://github.com/davidteather/TikTok-Api/tarball/main
Author: David Teather
Author-email: contact.davidteather@gmail.com
License: MIT
Keywords: tiktok,python3,api,unofficial,tiktok-api,tiktok api
Classifier: Development Status :: 4 - Beta
Classifier: Intended Audience :: Developers
Classifier: Topic :: Software Development :: Build Tools
Classifier: License :: OSI Approved :: MIT License
Classifier: Programming Language :: Python :: 3.9
Classifier: Programming Language :: Python :: 3.10
Classifier: Programming Language :: Python :: 3.11
Requires-Python: >=3.9
License-File: LICENSE
License-File: LICENSE.txt
Requires-Dist: requests
Requires-Dist: playwright
Requires-Dist: httpx
